{
  "identity": {
    "festival_id": "JP-c47f3b74",
    "name_en": "Hadaka Matsuri",
    "name_local": "裸祭り",
    "country": "Japan",
    "city": "Okayama",
    "category": "Traditional"
  },
  "schedule": {
    "start_date": "January",
    "end_date": "January",
    "frequency": "Annual",
    "season": "Winter"
  },
  "logistics": {
    "location": {
      "address": "Main square, Okayama, Japan",
      "coordinates": {
        "lat": 34.67,
        "lon": 133.95
      }
    },
    "access": "Public transportation, taxis, and local shuttles."
  },
  "multimedia": {
    "official_url": "https://www.okayama-hadaka.jp",
    "images": [
      "https://cdn.festa-global.com/JP/JP-c47f3b74_main.jpg"
    ],
    "videos": []
  },
  "resources": {
    "tickets": "Available via official website",
    "guide_url": "https://www.okayama-hadaka.jp/guide"
  },
  "verification": {
    "source": "Official Tourism Board",
    "last_updated": "2026-07-14",
    "status": "verified"
  }
}