{
  "identity": {
    "festival_id": "DE-a77ed9af",
    "name_en": "Bachfest Eisenach",
    "name_local": "Bachfest Eisenach",
    "country": "Germany",
    "city": "Eisenach",
    "category": "Music"
  },
  "schedule": {
    "start_date": "June",
    "end_date": "June",
    "frequency": "Annual",
    "season": "Summer"
  },
  "logistics": {
    "location": {
      "address": "Main square, Eisenach, Germany",
      "coordinates": {
        "lat": 50.84,
        "lon": 10.32
      }
    },
    "access": "Public transportation, taxis, and local shuttles."
  },
  "multimedia": {
    "official_url": "https://www.bachfest.de",
    "images": [
      "https://cdn.festa-global.com/DE/DE-a77ed9af_main.jpg"
    ],
    "videos": []
  },
  "resources": {
    "tickets": "Available via official website",
    "guide_url": "https://www.bachfest.de/guide"
  },
  "verification": {
    "source": "Official Tourism Board",
    "last_updated": "2026-07-14",
    "status": "verified"
  }
}